AUTHORS.rst
CONTRIBUTING.rst
HISTORY.rst
LICENSE
MANIFEST.in
README.rst
setup.cfg
setup.py
docs/Makefile
docs/authors.rst
docs/conf.py
docs/contributing.rst
docs/history.rst
docs/index.rst
docs/installation.rst
docs/jk.rst
docs/make.bat
docs/modules.rst
docs/readme.rst
docs/usage.rst
jk/__init__.py
jk.egg-info/PKG-INFO
jk.egg-info/SOURCES.txt
jk.egg-info/dependency_links.txt
jk.egg-info/not-zip-safe
jk.egg-info/top_level.txt
tests/__init__.py
tests/test_jk.py