Metadata-Version: 1.1
Name: jk
Version: 0.1.0
Summary: Library containing useful functions for manipulating iterables
Home-page: https://github.com/eliasdorneles/jk
Author: Elias Dorneles
Author-email: eliasdorneles@gmail.com
License: BSD
Keywords: jk
Platform: UNKNOWN
Classifier: Development Status :: 2 - Pre-Alpha
Classifier: Intended Audience :: Developers
Classifier: License :: OSI Approved :: BSD License
Classifier: Natural Language :: English
Classifier: Programming Language :: Python :: 2
Classifier: Programming Language :: Python :: 2.6
Classifier: Programming Language :: Python :: 2.7
Classifier: Programming Language :: Python :: 3
Classifier: Programming Language :: Python :: 3.3
Classifier: Programming Language :: Python :: 3.4
